pycount_mi/__init__.py
pycount_mi/plotting.py
pycount_mi/pycount_mi.py
pycount_mi-0.1.0.dist-info/LICENSE
pycount_mi-0.1.0.dist-info/WHEEL
pycount_mi-0.1.0.dist-info/METADATA
pycount_mi-0.1.0.dist-info/RECORD
